{
	"classic": {
		"truths": [
			"最近一次说的善意谎言是什么？",
			"你最怕的三件小事是？",
			"你手机里最常用的三个 App？",
			"你做过最冲动的决定是什么？",
			"你最想立刻学会的一项技能？",
			"你最近一次感到自豪的事情是什么？",
			"你最尴尬的一次社交经历？",
			"你最想删掉的一条朋友圈/动态是？",
			"你最想重新来过的一天是？",
			"你最离不开的生活小习惯？",
			"你最近偷偷感动的一件小事？",
			"你最怕被人发现的怪癖？",
			"你最喜欢的味道是什么？",
			"你在聚会里通常扮演什么角色？",
			"你最近一次熬夜在干嘛？",
			"你最想去但还没去过的城市？",
			"如果只能选一个季节过一年，你选哪个？",
			"你最想向谁道歉？",
			"你最不擅长拒绝的事情是？",
			"你最想拥有的超能力是什么？",
			"你最喜欢的零食是什么？",
			"你最难忘的一次旅行是？",
			"你最常对自己说的一句话？",
			"你最近一次被夸奖是什么？",
			"你最想拥有的宠物是什么？",
			"你最害怕的场景是什么？",
			"你最想挑战的一件事是什么？",
			"你最喜欢的一首歌是什么？",
			"你最想对未来的自己说什么？",
			"你最难忘的一顿饭是谁请的？"
		],
		"dares": [
			"用一种搞怪的方式自我介绍。",
			"用方言说一句祝酒词。",
			"模仿主持人报幕 15 秒。",
			"用 3 个词形容你右边的人。",
			"做 10 个深蹲。",
			"用歌声哼出一首大家都知道的歌。",
			"选择一个人对视 10 秒不笑。",
			"用表情包语气说一句台词。",
			"模仿你最常用的 emoji 动作。",
			"做一个夸张的胜利手势并保持 5 秒。",
			"说出一个冷笑话。",
			"向大家展示你手机里第一张照片的故事。",
			"用绕口令说：吃葡萄不吐葡萄皮。",
			"用夸张语气夸一次自己。",
			"用“播音腔”读出一句天气预报。",
			"在原地转 3 圈然后走直线。",
			"模仿电影里的一个经典动作。",
			"用 10 秒摆出 3 个不同表情。",
			"给大家做一个 5 秒的走秀。",
			"用一首歌的歌词回答下一个问题。",
			"为左边的人做一个 5 秒的“掌声特效”。",
			"用 10 秒编一个小广告。",
			"用夸张语气说：我太难了。",
			"用 3 个动作演示你的起床流程。",
			"用 10 秒模仿小动物。",
			"做一个“定格舞步”并保持 5 秒。",
			"给大家比心并说一句祝福。",
			"现场编一个 5 秒的口号。",
			"做一个“胜利pose”并说“我赢了”。",
			"用夸张语气读出你的手机电量。"
		]
	},
	"campus": {
		"truths": [
			"你最喜欢的一门课是什么？",
			"你上课最容易被点名的一次经历？",
			"你最想补回的一次早八是？",
			"你在宿舍最常做的事？",
			"你最难忘的一次社团活动？",
			"你最喜欢的食堂窗口是？",
			"你最想和谁一起上自习？",
			"你上课最常坐的位置？",
			"你做过最拖延的一次作业？",
			"你最擅长的考试类型？",
			"你最怕的考试科目？",
			"你最常去的校内地点？",
			"你最想选修的一门课？",
			"你做过最疯狂的“临时抱佛脚”？",
			"你最想复刻的校园瞬间？",
			"你最喜欢的一位老师？",
			"你最讨厌的校园规则？",
			"你最想体验的一次校园活动？",
			"你最难忘的军训瞬间？",
			"你最喜欢的校内小吃？",
			"你最难忘的一次考试分数？",
			"你最想带谁一起逃课？",
			"你最常用的学习 APP？",
			"你最想拥有的校园技能？",
			"你最想对新生说的一句话？",
			"你最喜欢的校园风景？",
			"你最想挑战的课程项目？",
			"你最常用的学习方法？",
			"你最难忘的一次晚归经历？",
			"你最喜欢的校园季节？"
		],
		"dares": [
			"用“班主任语气”说一句提醒。",
			"模仿上课点名的场景。",
			"用 10 秒讲一个宿舍趣事。",
			"做一个“课间操”动作。",
			"用 10 秒推销你的专业。",
			"模仿食堂阿姨打饭的动作。",
			"用 5 秒展示你的“早八脸”。",
			"用 10 秒展示你的“考试前复习”动作。",
			"即兴背一段你会的课文/公式。",
			"用 10 秒模仿图书馆安静手势。",
			"用 10 秒演示你“赶早八”的步伐。",
			"用 10 秒演示你“下课冲食堂”的动作。",
			"用 10 秒演示你“抢座位”的动作。",
			"用 10 秒演示你“考前抱佛脚”的动作。",
			"模仿一次课堂小组汇报。",
			"用 10 秒模仿宿管阿姨查寝。",
			"给大家讲一个你听过的校园梗。",
			"用 10 秒演示“晚自习困了”。",
			"用 10 秒演示“考试后松一口气”。",
			"用 10 秒演示“上课偷偷玩手机”。",
			"用 10 秒演示“被老师点名”。",
			"即兴编一个校园社团招新词。",
			"模仿你最喜欢的老师说一句话。",
			"用 10 秒展示“下雨天赶课”。",
			"用 10 秒展示“排队买奶茶”。",
			"用 10 秒展示“宿舍断网”。",
			"用 10 秒展示“发作业成绩”。",
			"用 10 秒展示“期末冲刺”。",
			"用 10 秒展示“运动会加油”。",
			"用 10 秒展示“毕业合照摆姿势”。"
		]
	},
	"couple": {
		"truths": [
			"你最喜欢对方哪一个小习惯？",
			"你最想和对方一起完成的事？",
			"你第一次心动的瞬间是？",
			"你最想收到的惊喜是什么？",
			"你最喜欢的一次约会是？",
			"你最想和对方一起去的地方？",
			"你觉得对方最可爱的表情是？",
			"你最希望对方改掉的一个小毛病？",
			"你最喜欢的称呼是什么？",
			"你最难忘的一次纪念日？",
			"你最想一起养的宠物？",
			"你最希望对方懂你的哪一点？",
			"你觉得对方最有魅力的瞬间？",
			"你最想一起完成的旅行清单？",
			"你最喜欢的相处方式？",
			"你最想对对方说的一句感谢？",
			"你最在意的恋爱仪式感？",
			"你最想一起尝试的兴趣？",
			"你最想一起看的电影类型？",
			"你觉得对方像哪一种天气？",
			"你最喜欢对方做的哪道菜？",
			"你最想收到的手写内容？",
			"你最想一起拍的一张照片主题？",
			"你最喜欢对方的哪句口头禅？",
			"你最希望对方记住的一个小细节？",
			"你最想一起去的演出/展览？",
			"你最想一起完成的挑战？",
			"你最想给对方准备的礼物类型？",
			"你最喜欢的一段聊天记录？",
			"你最想和对方分享的一首歌？"
		],
		"dares": [
			"用一句话夸对方三次。",
			"给对方一个 10 秒的拥抱。",
			"用 10 秒描述对方的优点。",
			"用对方的口头禅说一句话。",
			"给对方做一个 5 秒的肩部按摩。",
			"用对方的语气说一句“我在”。",
			"给对方唱一句你会的歌。",
			"给对方写下一个小心愿。",
			"和对方击掌 3 次并说“配合”。",
			"用 5 秒模仿对方走路的样子。",
			"给对方一个“假装惊喜”的表情。",
			"用 10 秒描述一次理想约会。",
			"对对方说一句“谢谢你”。",
			"用 10 秒演示你的“撒娇模式”。",
			"把对方的名字写在空气里。",
			"和对方做一个同步动作。",
			"用 10 秒说一个你们的共同回忆。",
			"对对方说一句“今天也辛苦啦”。",
			"用 10 秒模仿你们第一次见面。",
			"给对方一个“专属昵称”并解释。",
			"用 10 秒为对方设计一个超能力。",
			"说一句“下次一起去……”。",
			"用 10 秒讲一个你们未来的小计划。",
			"给对方一个“我懂你”的眼神。",
			"用 10 秒比划一个“爱的手势”。",
			"对对方说一句“我相信你”。",
			"用 10 秒描述对方的一天。",
			"用 10 秒讲一个“我们”的梦想。",
			"用 10 秒表达一次你的小感动。",
			"对对方说一句“我们一起加油”。"
		]
	},
	"online": {
		"truths": [
			"你最常用的聊天表情包是？",
			"你最常发的一个字是什么？",
			"你最近一次“已读不回”的原因？",
			"你最想拥有的聊天头像风格？",
			"你最常用的聊天开场白？",
			"你最怕收到的聊天消息类型？",
			"你最想在群里说但没说的一句话？",
			"你最近一次深夜聊天的主题？",
			"你最想屏蔽的群类型？",
			"你最想删掉的一条聊天记录？",
			"你最喜欢的聊天语音长度？",
			"你最喜欢的聊天称呼？",
			"你最喜欢的网络梗是？",
			"你最想设置的个性签名？",
			"你最常用的社交平台？",
			"你最不想被谁看到的动态？",
			"你最喜欢的聊天时间段？",
			"你最喜欢的聊天气泡颜色？",
			"你最想拥有的表情包主题？",
			"你最想改变的一次聊天误会？",
			"你最喜欢的一句网络用语？",
			"你最常用的截图内容类型？",
			"你最想给自己的昵称起什么？",
			"你最喜欢的群昵称格式？",
			"你最常用的短语缩写？",
			"你最不想收到的“早安/晚安”是什么？",
			"你最想收藏的一条消息是什么？",
			"你最常用的语音语气？",
			"你最喜欢的聊天背景图风格？",
			"你最常用的“已读回复”方式？"
		],
		"dares": [
			"用输入法联想写一句话并读出来。",
			"用 10 秒模仿语音消息语气。",
			"用 3 个表情讲一个小故事。",
			"用“哈哈哈”写一段 10 字回复。",
			"用“语音转文字”的口吻说一句话。",
			"用 5 秒模仿网络主播口吻。",
			"把你手机里最近用的表情描述出来。",
			"用 10 秒模仿机器人客服说话。",
			"用 10 秒模仿语音条卡顿。",
			"用 10 秒模仿“撤回一条消息”的反应。",
			"用 10 秒模仿“突然断网”的表情。",
			"用 10 秒模仿“抢红包”的动作。",
			"用 10 秒模仿“正在输入中”的紧张感。",
			"用 10 秒模仿“收到点赞通知”的开心。",
			"用 10 秒模仿“群里被点名”的反应。",
			"用 10 秒模仿“误发消息”的尴尬。",
			"用 10 秒模仿“语音太长没人听”。",
			"用 10 秒模仿“收到了红包”的开心。",
			"用 10 秒模仿“手机没电”的慌张。",
			"用 10 秒模仿“聊天被截图”的反应。",
			"用 10 秒模仿“群里@全体”的反应。",
			"用 10 秒模仿“视频通话来电”的反应。",
			"用 10 秒模仿“朋友圈被翻到底”。",
			"用 10 秒模仿“刷到旧动态”的反应。",
			"用 10 秒模仿“深夜消息提示”。",
			"用 10 秒模仿“消息未发送成功”。",
			"用 10 秒模仿“收到语音轰炸”。",
			"用 10 秒模仿“键盘敲击声”。",
			"用 10 秒模仿“疯狂点赞”。",
			"用 10 秒模仿“群里突然安静”。"
		]
	}
}
